README.md
setup.cfg
setup.py
djongo/__init__.py
djongo/admin.py
djongo/base.py
djongo/compiler.py
djongo/cursor.py
djongo/database.py
djongo/features.py
djongo/introspection.py
djongo/operations.py
djongo/schema.py
djongo/dynamic_formsets/__init__.py
djongo/dynamic_formsets/apps.py
djongo/dynamic_formsets/templatetags/__init__.py
djongo/dynamic_formsets/templatetags/formset_tags.py
djongo/models/__init__.py
djongo/models/fields.py
djongo/models/json.py
djongo/sql2mongo/__init__.py
djongo/sql2mongo/alter.py
djongo/sql2mongo/converters.py
djongo/sql2mongo/operators.py
djongo/sql2mongo/query.py
djongo_mongo_version_fix.egg-info/PKG-INFO
djongo_mongo_version_fix.egg-info/SOURCES.txt
djongo_mongo_version_fix.egg-info/dependency_links.txt
djongo_mongo_version_fix.egg-info/requires.txt
djongo_mongo_version_fix.egg-info/top_level.txt