Metadata-Version: 2.1
Name: djongo-mongo-version-fix
Version: 1.2.32
Summary: Driver for allowing Django to use MongoDB as the database backend.
Home-page: https://nesdis.github.io/djongo/
Author: raheem
Author-email: raheemazeez4@gmail.com
License: AGPL
Keywords: Django MongoDB driver connector
Platform: UNKNOWN
Classifier: Development Status :: 3 - Alpha
Classifier: Intended Audience :: Developers
Classifier: License :: OSI Approved :: BSD License
Classifier: Programming Language :: Python :: 3.6
Requires-Python: >=3.6
Provides-Extra: json
